README.md
setup.cfg
setup.py
cmdo/__init__.py
cmdo/cmdo.py
cmdo/dal.py
cmdo/display.py
cmdo/term.py
cmdo_App.egg-info/PKG-INFO
cmdo_App.egg-info/SOURCES.txt
cmdo_App.egg-info/dependency_links.txt
cmdo_App.egg-info/entry_points.txt
cmdo_App.egg-info/not-zip-safe
cmdo_App.egg-info/top_level.txt