Metadata-Version: 1.1
Name: cmdo-App
Version: 0.3
Summary: Cmdo: the command line todo list app
Home-page: http://github.com/kaundur/cmdo
Author: Kaundur
Author-email: cmdo@kaundur.com
License: MIT
Download-URL: https://github.com/kaundur/cmdo/archive/0.3.tar.gz
Keywords: todo,todolist,todoapp,command-line-tool,command-line,python,productivity
Platform: UNKNOWN
